tensorboardY/__init__.py
tensorboardY/__version__.py
tensorboardY/output.py
tensorboardY/server.py
tensorboardY/tools.py
tensorboardY/widgets.py
tensorboardY/frontend/index.html
tensorboardY/frontend/css/main.css
tensorboardY/frontend/favicon/android-chrome-192x192.png
tensorboardY/frontend/favicon/android-chrome-512x512.png
tensorboardY/frontend/favicon/apple-touch-icon.png
tensorboardY/frontend/favicon/favicon-16x16.png
tensorboardY/frontend/favicon/favicon-32x32.png
tensorboardY/frontend/favicon/favicon.ico
tensorboardY/frontend/favicon/site.webmanifest
tensorboardY/frontend/js/main.js
tensorboardY-0.1.9.dist-info/LICENSE
tensorboardY-0.1.9.dist-info/METADATA
tensorboardY-0.1.9.dist-info/WHEEL
tensorboardY-0.1.9.dist-info/top_level.txt
tensorboardY-0.1.9.dist-info/RECORD
